yhttp/core/__init__.py
yhttp/core/application.py
yhttp/core/cli.py
yhttp/core/contenttypes.py
yhttp/core/guard.py
yhttp/core/headerset.py
yhttp/core/lazyattribute.py
yhttp/core/main.py
yhttp/core/multidict.py
yhttp/core/multipart.py
yhttp/core/request.py
yhttp/core/response.py
yhttp/core/rewrite.py
yhttp/core/static.py
yhttp/core/statuses.py
yhttp/core/version.py
yhttp-7.0.4.dist-info/licenses/LICENSE
yhttp-7.0.4.dist-info/METADATA
yhttp-7.0.4.dist-info/WHEEL
yhttp-7.0.4.dist-info/entry_points.txt
yhttp-7.0.4.dist-info/top_level.txt
yhttp-7.0.4.dist-info/RECORD
